vbpr/__init__.py
vbpr/datasets/README.md
vbpr/datasets/__init__.py
vbpr/datasets/tradesy.py
vbpr/trainer.py
vbpr/vbpr.py
vbpr_pytorch-0.1.2.dist-info/LICENSE
vbpr_pytorch-0.1.2.dist-info/METADATA
vbpr_pytorch-0.1.2.dist-info/WHEEL
vbpr_pytorch-0.1.2.dist-info/RECORD
