Metadata-Version: 2.1
Name: vbpr-pytorch
Version: 0.1.2
Summary: Implementation of VBPR, a visual recommender model, from the paper 'VBPR: Visual Bayesian Personalized Ranking from Implicit Feedback'
Home-page: https://github.com/aaossa/VBPR-PyTorch
License: MIT
Keywords: artificial intelligence,recommender systems,vbpr
Author: Antonio Ossa-Guerra
Author-email: aaossa@uc.cl
Requires-Python: >=3.8.1,<3.12
Classifier: Development Status :: 3 - Alpha
Classifier: Intended Audience :: Developers
Classifier: License :: OSI Approved :: MIT License
Classifier: Programming Language :: Python
Classifier: Programming Language :: Python :: 3
Classifier: Programming Language :: Python :: 3.9
Classifier: Programming Language :: Python :: 3.10
Classifier: Programming Language :: Python :: 3.11
Classifier: Topic :: Scientific/Engineering :: Artificial Intelligence
Provides-Extra: wandb
Requires-Dist: numpy (>=1.24.2,<2.0.0)
Requires-Dist: pandas (>=1.5.3)
Requires-Dist: torch (>=1.13.1,!=2.0.1,!=2.1.0)
Requires-Dist: tqdm (>=4.64.1,<5.0.0)
Requires-Dist: wandb (>=0.13.10,<0.14.0) ; extra == "wandb"
Project-URL: Repository, https://github.com/aaossa/VBPR-PyTorch
